fontparse/__init__.py
fontparser-0.1.1.dist-info/METADATA
fontparser-0.1.1.dist-info/WHEEL
fontparser-0.1.1.dist-info/licenses/LICENSE
fontparser-0.1.1.dist-info/RECORD
