Metadata-Version: 2.1
Name: fontparser
Version: 0.1.1
Summary: font file parser library in Python
Project-URL: Homepage, https://github.com/duoduo6666/font-parser
Project-URL: Issues, https://github.com/duoduo6666/font-parser/issues
Project-URL: GitHub, https://github.com/duoduo6666/font-parser
Project-URL: GitLab, https://gitlab.duo-duo.top/root/fontparser
Author-email: duoduo <duoduoqaq520@gmail.com>
License-File: LICENSE
Classifier: License :: OSI Approved :: MIT License
Classifier: Operating System :: OS Independent
Classifier: Programming Language :: Python :: 3
Requires-Python: >=3.10.2
Requires-Dist: numpy
Requires-Dist: opencv-python
